{"Old Church Slavonic": ["\u043a\u0440\u0430\u0442\u044a\u043a\u044a", "kratu\u0306ku\u0306"], "Romansh": ["curt", ""], "Vlach": ["SKURTU", ""], "Slovenian": ["KRATKO", ""], "Russian P": ["KOROTKIJ", ""], "Ladin": ["CUORT", ""], "Armenian List": ["GARJ", ""], "Brazilian": ["CURTO", ""], "Albanian K": ["I SKURTERE", ""], "Byelorussian": ["KAROTKI, KAROTKA", ""], "Serbocroatian": ["KRATAK", ""], "Ukrainian P": ["KOROTKYJ", ""], "Ukrainian": ["KOROTKYJ", ""], "Portuguese St": ["curto", "\u02c8ku\u027etu"], "Albanian Top": ["SKURTER", ""], "French": ["court", "ku\u0280"], "Macedonian P": ["KRATOK", ""], "Catalan": ["curt", "ku\u027e"], "Dolomite Ladino": ["curt", ""], "Serbocroatian P": ["kratak", "kr\u01cetak"], "Russian": ["\u043a\u043e\u0440\u043e\u0442\u043a\u0438\u0439", "ko'rotk\u0268j"], "Slovak P": ["KRATKY", ""], "_MEANING": "short", "Classical Armenian": ["kar\u010d", ""], "Standard Albanian": ["i, e shkurt\u00ebr", ""], "Rumanian List": ["scurt", ""], "Sardinian C": ["KURCU", ""], "Sardinian N": ["KURTHU", ""], "Sardinian L": ["CURZU", ""], "Czech E": ["KRATKE", ""], "Armenian Mod": ["kar\u010d", "k\u0251\u027e\u02a7"], "Polish P": ["KROTKI", ""], "Bulgarian P": ["KRATUK", ""], "Albanian": ["SHKURT", ""], "Slovenian P": ["KRATEK", ""], "English": ["short", "\u0283\u0254:t"], "Byelorussian P": ["KAROTKI", ""], "Serbian": ["kratak", "kr\u01cetak"], "Old English": ["scort", ""], "Italian": ["corto", "'korto"], "Czech P": ["KRATKY", ""], "Walloon": ["COURT", ""], "Czech": ["kr\u00e1tk\u00fd", "kra\u02d0tki\u02d0"], "Sranan": ["SJATOE", ""], "French Creole D": ["KUT", ""], "Albanian T": ["i shkurt\u00ebr", ""], "French Creole C": ["KUT", ""], "Macedonian": ["kratok", "\u02c8krat\u0254k"], "Upper Sorbian": ["KROTKI", ""], "Slovak": ["KRATKY", ""], "Friulian": ["curt", ""], "Spanish": ["corto", "'ko\u027eto"], "Lower Sorbian": ["KROTKI", ""], "Polish": ["kr\u00f3tki", "\u02c8krutk\u02b2i"], "Albanian C": ["I-SKURTUR", ""], "Albanian G": ["SHKURT", ""]}