{"Swedish": ["skinn", "\u0267\u026an\u02d0"], "Danish": ["skind", "s\u0261\u030a\u02b0en\u02c0"], "Icelandic St": ["skinn", "sc\u026an\u02d0"], "Swedish Up": ["SKINN", ""], "\u00d6vdalian": ["stjinn", "st\u0283\u026an\u02d0"], "Old Swedish": ["skin", "skin\u02d0"], "Old Norse": ["skinn", "skin\u02d0"], "Stavangersk": ["sjinn", "\u0282\u026an\u02d0"], "Norwegian": ["skinn", "\u0283\u026an\u02d0"], "English": ["skin", "sk\u026an"], "Faroese": ["SKINN", ""], "Gutnish Lau": ["skinn", "sk\u026an\u02d0"], "Danish Fjolde": ["skind", "sxin\u02b2"], "Swedish Vl": ["SIN", ""], "_MEANING": "skin"}