{"Swedish": ["glatt", "glat\u02d0"], "Old Church Slavonic": ["\u0433\u043b\u0430\u0434\u044a\u043a\u044a", "gladu\u0306ku\u0306"], "Slovenian P": ["GLADEK", ""], "Slovenian": ["GLADKO", ""], "Russian P": ["GLADKIJ", ""], "Dutch List": ["gelijk, glad", "\u0263\u0259'l\u025bik, \u0263l\u0251t"], "L\u00ebtzebuergesch": ["glat", ""], "Byelorussian": ["HLADKI", ""], "Danish": ["glat", "g\u0325lad\u0325\u02b0"], "Bulgarian": ["gladak", "\u02c8\u0261lad\u0264k"], "Ukrainian P": ["HLADKYJ", ""], "Ukrainian": ["HLADKYJ, RIVNYJ", ""], "Stavangersk": ["glatte", "\u02c8\u0261lat\u02d0\u0259"], "Norwegian": ["glatt", "\u0261lat\u02d0"], "Serbocroatian P": ["gladak", "\u0261l\u00e2dak"], "Russian": ["\u0433\u043b\u0430\u0434\u043a\u0438\u0439", "'gladk\u0268j"], "Slovak P": ["HLADKY", ""], "Afrikaans": ["GLAD, SAG", ""], "_MEANING": "smooth", "Serbocroatian": ["GLADAK", ""], "Polish P": ["GLADKI", ""], "Bulgarian P": ["GLADUK", ""], "Latvian": ["glud\u0119ns", ""], "Serbian": ["gladak", "\u0261l\u00e2dak"], "Byelorussian P": ["HLADKI", ""], "Pennsylvania Dutch": ["GLOT", ""], "Frisian": ["GLAD", ""], "Czech P": ["HLADKY", ""], "Standard German (Munich)": ["glatt", ""], "Schwyzerd\u00fctsch": ["glatt", ""], "Czech": ["hladk\u00fd", "\u0266latki\u02d0"], "Sranan": ["GLATI", ""], "Flemish": ["GLAD", ""], "German": ["glatt", "glat"], "Upper Sorbian": ["HLADKI", ""], "Slovak": ["HLADKY", ""], "Czech E": ["HLADKE", ""], "Lower Sorbian": ["GLADKI", ""], "Polish": ["g\u0142adki", "\u02c8\u0261watki"], "Danish Fjolde": ["gl\u00e6j", "\u0261l\u00e6j"]}