{"Walloon": ["PACE QUI", ""], "Ladin": ["PERVI CHA", ""], "Sardinian N": ["PROKE", ""], "Portuguese St": ["porque", "\u02c8pu\u027ek\u0268"], "Spanish": ["porque", "'po\u027eke"], "Romansh": ["perquai che", ""], "French": ["parce que", "pa\u0280s(\u0259) k(\u0259)"], "Catalan": ["perqu\u00e8", "p\u0259r'k\u025b"], "Dolomite Ladino": ["parcie, parc\u00e8", ""], "Provencal": ["PER-CO-QUE", ""], "Friulian": ["parc\u00e8, parc\u00e8 che", ""], "Brazilian": ["PORQUE", ""], "_MEANING": "because", "Italian": ["perch\u00e8", "per'ke"]}