{"Czech P": ["CHLADNY", ""], "Old Church Slavonic": ["\u0445\u043b\u0430\u0434\u044c\u043d\u044a", ""], "Serbocroatian": ["HLADNO", ""], "Ukrainian": ["XOLODNO", ""], "Czech": ["chladn\u00fd", "xladni"], "Serbian": ["hladno", "xl\u01ce\u02d0dno"], "Ukrainian P": ["CHOLODNYJ", ""], "Russian P": ["CHOLODNYJ", ""], "Macedonian P": ["CHLADEN", ""], "Macedonian": ["LADEN", ""], "Upper Sorbian": ["KHLODNY", ""], "Slovenian P": ["HLADEN", ""], "Serbocroatian P": ["hladno\u0107a", "xladn\u01d2t\u0255a"], "Lower Sorbian": ["CHLODNY", ""], "Byelorussian P": ["CHALODNY", ""], "Byelorussian": ["S'CJUDZENA", ""], "Polish P": ["CHLODNY", ""], "_MEANING": "cold", "Slovak P": ["CHLADNY", ""], "Russian": ["\u0445\u043e\u043b\u043e\u0434\u043d\u044b\u0439", "xo'lodn\u0268j"]}