{"Marathi": ["t\u012bksna", "'ti:k\u0282\u0273\u0259"], "Vedic Sanskrit": ["ti\u0304k\u1e63\u1e47\u00e1s", ""], "Pashto": ["TERE", ""], "Shughni": ["te\u0304z", ""], "Hindi": ["TEJ", ""], "Panjabi St": ["TIKKHA", ""], "Wakhi": ["TEGHD, TIZ", ""], "Digor Ossetic": ["\u010dir\u0281", "\u010dir\u0281"], "Bihari": ["tejg\u0259r", "tejg\u0259r"], "Iron Ossetic": ["syr\u0281", "syr\u0281"], "Waziri": ["TERA", ""], "Lahnda": ["TEZ", ""], "_MEANING": "sharp", "Kashmiri": ["TEZ", ""], "Sogdian": ["tr\u03b3", ""], "Baluchi": ["TEZ", ""], "Sariqoli": ["t\u025byd", ""], "Ossetic": ["cyrg'", "ts\u0268r\u0281"], "Old Persian": ["tigra", ""], "Tadzik": ["TEZ", ""], "Avestan": ["ti\u03b3r\u014d", ""], "Persian": ["TIZ", ""], "Marwari": ["tikho", "tikho"], "Urdu": ["\u062a\u06cc\u0632", "t\u032aez"]}